tupu/__init__.py
tupu/__version__.py
tupu/distance.py
tupu/geoindex.py
tupu/io.py
tupu/table.py
tupu/utils.py
tupu-0.1.0.dist-info/LICENSE
tupu-0.1.0.dist-info/METADATA
tupu-0.1.0.dist-info/WHEEL
tupu-0.1.0.dist-info/entry_points.txt
tupu-0.1.0.dist-info/top_level.txt
tupu-0.1.0.dist-info/RECORD
