Metadata-Version: 2.1
Name: tupu
Version: 0.1.0
Summary: Fast geodesic distances between sets
Home-page: https://github.com/sergiocorreia/tupu
Author: Sergio Correia
Author-email: sergio.correia@gmail.com
License: MIT
Platform: UNKNOWN
Classifier: License :: OSI Approved :: BSD License
Classifier: Programming Language :: Python
Classifier: Programming Language :: Python :: 3
Classifier: Programming Language :: Python :: 3.7
Classifier: Programming Language :: Python :: 3.8
Classifier: Programming Language :: Python :: Implementation :: CPython
Classifier: Development Status :: 3 - Alpha
Requires-Python: >=3.7.0
Requires-Dist: pyproj
Requires-Dist: rtree
